openlxp_notifications/__init__.py
openlxp_notifications/admin.py
openlxp_notifications/apps.py
openlxp_notifications/models.py
openlxp_notifications/serializer.py
openlxp_notifications/urls.py
openlxp_notifications/views.py
openlxp_notifications/management/__init__.py
openlxp_notifications/management/commands/__init__.py
openlxp_notifications/management/commands/trigger_status_update.py
openlxp_notifications/management/commands/trigger_subscribed_list_update.py
openlxp_notifications/management/utils/__init__.py
openlxp_notifications/management/utils/ses_client.py
openlxp_notifications/management/utils/ses_configuration.py
openlxp_notifications/migrations/0001_initial.py
openlxp_notifications/migrations/0002_rename_logs_type_emailconfiguration_content_type.py
openlxp_notifications/migrations/0003_emailconfiguration_banner.py
openlxp_notifications/migrations/0004_auto_20240530_1646.py
openlxp_notifications/migrations/__init__.py
openlxp_notifications/templates/__init__.py
openlxp_notifications/templates/status_update_template.html
openlxp_notifications/tests/__init__.py
openlxp_notifications/tests/test_setup.py
openlxp_notifications/tests/test_xia_command_unit.py
openlxp_notifications/tests/test_xia_models_unit.py
openlxp_notifications/tests/test_xia_utils_unit.py
openlxp_notifications_project/__init__.py
openlxp_notifications_project/asgi.py
openlxp_notifications_project/settings.py
openlxp_notifications_project/urls.py
openlxp_notifications_project/wsgi.py
venv/bin/django-admin.py
venv/bin/jp.py
openlxp_notification-1.4.6.dist-info/METADATA
openlxp_notification-1.4.6.dist-info/WHEEL
openlxp_notification-1.4.6.dist-info/top_level.txt
openlxp_notification-1.4.6.dist-info/RECORD
